setup.cfg
setup.py
TracCaptcha.egg-info/PKG-INFO
TracCaptcha.egg-info/SOURCES.txt
TracCaptcha.egg-info/dependency_links.txt
TracCaptcha.egg-info/entry_points.txt
TracCaptcha.egg-info/not-zip-safe
TracCaptcha.egg-info/requires.txt
TracCaptcha.egg-info/top_level.txt
trac_captcha/__init__.py
trac_captcha/api.py
trac_captcha/compat.py
trac_captcha/controller.py
trac_captcha/cryptobox.py
trac_captcha/i18n.py
trac_captcha/release.py
trac_captcha/ticket.py
trac_captcha/trac_version.py
trac_captcha/lib/__init__.py
trac_captcha/lib/attribute_dict.py
trac_captcha/lib/distribution_helpers.py
trac_captcha/lib/simple_super.py
trac_captcha/lib/testcase.py
trac_captcha/lib/version.py
trac_captcha/locale/__init__.py
trac_captcha/locale/de/__init__.py
trac_captcha/locale/de/LC_MESSAGES/__init__.py
trac_captcha/test_util/__init__.py
trac_captcha/test_util/captcha_test.py
trac_captcha/test_util/compat.py
trac_captcha/test_util/fake_captcha.py
trac_captcha/test_util/trac_test.py
trac_recaptcha/__init__.py
trac_recaptcha/client.py
trac_recaptcha/genshi_widget.py
trac_recaptcha/integration.py