Metadata-Version: 1.0
Name: TracCaptcha
Version: 0.3
Summary: pluggable captcha infrastructure for Trac with reCAPTCHA included
Home-page: http://www.schwarz.eu/opensource/projects/trac_captcha
Author: Felix Schwarz
Author-email: felix.schwarz@oss.schwarz.eu
License: MIT
Download-URL: http://www.schwarz.eu/opensource/projects/TracCaptcha/download/0.3/TracCaptcha-0.3.tar.gz
Platform: UNKNOWN
Classifier: Development Status :: 4 - Beta
Classifier: Framework :: Trac
Classifier: Intended Audience :: System Administrators
Classifier: License :: OSI Approved :: MIT License
Classifier: Operating System :: OS Independent
Classifier: Programming Language :: Python
Classifier: Topic :: Software Development :: Libraries :: Python Modules
